Makefile
README.txt
ez_setup.py
setup.py
examples/es.txt
examples/example.py
examples/example.txt
examples/urlsum.py
lib/ots-0.4.2+cvs.2004.02.20.tar.bz2
ots.egg-info/PKG-INFO
ots.egg-info/SOURCES.txt
ots.egg-info/native_libs.txt
ots.egg-info/top_level.txt
src/ots.c
src/ots.pyx
