Metadata-Version: 1.0
Name: ots
Version: 0.4.2.1
Summary: Python bindings around libots. For summarizing text.
Home-page: UNKNOWN
Author: Benjamin Saller
Author-email: bcsaller@objectrealms.net
License: GPL 2.1
Keywords: text topics summarizing classification
Platform: UNKNOWN
